MANIFEST.in
README.md
setup.cfg
setup.py
opencypher/__init__.py
opencypher/api.py
opencypher.egg-info/PKG-INFO
opencypher.egg-info/SOURCES.txt
opencypher.egg-info/dependency_links.txt
opencypher.egg-info/not-zip-safe
opencypher.egg-info/requires.txt
opencypher.egg-info/top_level.txt
opencypher/ast/__init__.py
opencypher/ast/clause.py
opencypher/ast/collection.py
opencypher/ast/create.py
opencypher/ast/cypher.py
opencypher/ast/delete.py
opencypher/ast/expression.py
opencypher/ast/formatting.py
opencypher/ast/function.py
opencypher/ast/match.py
opencypher/ast/merge.py
opencypher/ast/naming.py
opencypher/ast/ordering.py
opencypher/ast/paging.py
opencypher/ast/parameter.py
opencypher/ast/properties.py
opencypher/ast/query.py
opencypher/ast/remove.py
opencypher/ast/return_.py
opencypher/ast/set.py
opencypher/ast/unwind.py
opencypher/ast/pattern/__init__.py
opencypher/ast/pattern/base.py
opencypher/ast/pattern/node.py
opencypher/ast/pattern/relationship.py
opencypher/builder/__init__.py
opencypher/builder/clause.py
opencypher/builder/cypher.py
opencypher/builder/expression.py
opencypher/builder/pattern.py
opencypher/builder/return_.py
opencypher/builder/union.py
opencypher/builder/write.py