Metadata-Version: 2.1
Name: opencypher
Version: 0.3.0
Summary: OpenCypher AST and Builder API
Home-page: https://github.com/globality-corp/opencypher
Author: Globality Engineering
Author-email: engineering@globality.com
License: Apache 2.0
Keywords: opencypher cypher neo4j
Platform: UNKNOWN
Classifier: Programming Language :: Python :: 3.7
Requires-Python: >=3.7
Provides-Extra: test
